markovify/__init__.py
markovify/__version__.py
markovify/chain.py
markovify/splitters.py
markovify/text.py
markovify/utils.py
markovify-0.9.4.dist-info/licenses/LICENSE.txt
markovify-0.9.4.dist-info/METADATA
markovify-0.9.4.dist-info/WHEEL
markovify-0.9.4.dist-info/namespace_packages.txt
markovify-0.9.4.dist-info/top_level.txt
markovify-0.9.4.dist-info/RECORD
