Metadata-Version: 2.1
Name: markovify
Version: 0.9.4
Summary: A simple, extensible Markov chain generator. Uses include generating random semi-plausible sentences based on an existing text.
Home-page: http://github.com/jsvine/markovify
Author: Jeremy Singer-Vine
Author-email: jsvine@gmail.com
License: MIT
Keywords: markov chain text
Platform: UNKNOWN
Classifier: Intended Audience :: Developers
Classifier: License :: OSI Approved :: MIT License
Classifier: Operating System :: OS Independent
Classifier: Programming Language :: Python :: 3.6
Classifier: Programming Language :: Python :: 3.7
Classifier: Programming Language :: Python :: 3.8
Classifier: Programming Language :: Python :: 3.9
Requires-Python: >=3.6
License-File: LICENSE.txt
